loqet/__init__.py
loqet/cli_utils.py
loqet/encryption_suite.py
loqet/exceptions.py
loqet/file_utils.py
loqet/loq_cli.py
loqet/loqet_cli.py
loqet/loqet_configs.py
loqet/loqet_context_cli.py
loqet/loqet_contexts.py
loqet/secret_keys.py
loqet/secret_store.py
loqet-0.0.3.dist-info/LICENSE
loqet-0.0.3.dist-info/METADATA
loqet-0.0.3.dist-info/WHEEL
loqet-0.0.3.dist-info/entry_points.txt
loqet-0.0.3.dist-info/top_level.txt
loqet-0.0.3.dist-info/RECORD
