Metadata-Version: 2.1
Name: loqet
Version: 0.0.3
Summary: Local secrets manager in python
Home-page: https://github.com/JaceTSM/loqet
Author: Tim Murphy
Author-email: jac3tssm@gmail.com
License: UNKNOWN
Platform: UNKNOWN
Classifier: Programming Language :: Python :: 3
Classifier: License :: OSI Approved :: BSD License
Classifier: Operating System :: OS Independent
Requires-Python: >=3.6
License-File: LICENSE
Requires-Dist: cryptography
Requires-Dist: pyyaml
